README.rst
setup.py
sklearn_extras/__init__.py
sklearn_extras/extractors.py
sklearn_extras/preprocessing.py
sklearn_extras.egg-info/PKG-INFO
sklearn_extras.egg-info/SOURCES.txt
sklearn_extras.egg-info/dependency_links.txt
sklearn_extras.egg-info/top_level.txt