Metadata-Version: 1.1
Name: sklearn_extras
Version: 0.1.1
Summary: Some extra stuffs that I always use
Home-page: https://github.com/arielrossanigo/sklearn_extras
Author: Ariel Rossanigo
Author-email: arielrossanigo@gmail.com
License: UNKNOWN
Keywords: machine learning,scikit,scikit-learn,sklearn
Platform: UNKNOWN
Classifier: Programming Language :: Python
Classifier: Programming Language :: Python :: 2
Classifier: Programming Language :: Python :: 2.7
Classifier: Programming Language :: Python :: 3
Classifier: Programming Language :: Python :: 3.5
Classifier: Intended Audience :: Developers
Classifier: Operating System :: OS Independent
Classifier: Topic :: Scientific/Engineering
Classifier: Topic :: Scientific/Engineering :: Artificial Intelligence
Classifier: Topic :: Software Development :: Libraries
